{
  "network_structure": {
    "nodes": [
      "FS_TotCort_GM_Vol",
      "FS_SubCort_GM_Vol",
      "FS_Total_GM_Vol",
      "FS_Tot_WM_Vol",
      "FS_BrainStem_Vol",
      "FS_L_Hippo_Vol",
      "FS_R_Hippo_Vol",
      "FS_L_Amygdala_Vol",
      "FS_R_Amygdala_Vol",
      "FS_L_Caudate_Vol",
      "FS_R_Caudate_Vol",
      "FS_L_Putamen_Vol",
      "FS_R_Putamen_Vol",
      "Age",
      "Gender",
      "CogFluidComp_Unadj",
      "CogCrystalComp_Unadj",
      "MMSE_Score",
      "NEOFAC_O",
      "NEOFAC_C",
      "ProcSpeed_Unadj",
      "CardSort_Unadj",
      "PicVocab_Unadj",
      "ReadEng_Unadj"
    ],
    "edges": [
      [
        "FS_Total_GM_Vol",
        "CogFluidComp_Unadj"
      ],
      [
        "FS_Tot_WM_Vol",
        "CogFluidComp_Unadj"
      ],
      [
        "FS_Total_GM_Vol",
        "CogCrystalComp_Unadj"
      ],
      [
        "FS_Tot_WM_Vol",
        "CogCrystalComp_Unadj"
      ],
      [
        "Age",
        "MMSE_Score"
      ],
      [
        "FS_L_Hippo_Vol",
        "NEOFAC_O"
      ],
      [
        "FS_R_Hippo_Vol",
        "NEOFAC_O"
      ]
    ],
    "FS_TotCort_GM_Vol": {
      "parents": [],
      "parameters": null,
      "distribution": "(-0.026512854494606906, 0.9929502916199376)"
    },
    "FS_SubCort_GM_Vol": {
      "parents": [],
      "parameters": null,
      "distribution": "(-0.12796543910590333, 0.9999610765107816)"
    },
    "FS_Total_GM_Vol": {
      "parents": [],
      "parameters": null,
      "distribution": "(-0.0493680304751006, 1.0088600529633258)"
    },
    "FS_Tot_WM_Vol": {
      "parents": [],
      "parameters": null,
      "distribution": "(-0.10018982695240783, 0.9650019259574558)"
    },
    "FS_BrainStem_Vol": {
      "parents": [],
      "parameters": null,
      "distribution": "(-0.17392631653645926, 0.9824779436058143)"
    },
    "FS_L_Hippo_Vol": {
      "parents": [],
      "parameters": null,
      "distribution": "(-0.03822659972777986, 1.194029612914668)"
    },
    "FS_R_Hippo_Vol": {
      "parents": [],
      "parameters": null,
      "distribution": "(-0.044108271826220014, 1.0812777424739242)"
    },
    "FS_L_Amygdala_Vol": {
      "parents": [],
      "parameters": null,
      "distribution": "(-0.0857288279357955, 0.9898688258618746)"
    },
    "FS_R_Amygdala_Vol": {
      "parents": [],
      "parameters": null,
      "distribution": "(-0.12402322546991225, 1.0317573409592755)"
    },
    "FS_L_Caudate_Vol": {
      "parents": [],
      "parameters": null,
      "distribution": "(-0.019238482608895744, 0.9814465823893189)"
    },
    "FS_R_Caudate_Vol": {
      "parents": [],
      "parameters": null,
      "distribution": "(-0.011347171531528654, 1.0216285008567934)"
    },
    "FS_L_Putamen_Vol": {
      "parents": [],
      "parameters": null,
      "distribution": "(-0.14197660525613764, 0.9464123194464621)"
    },
    "FS_R_Putamen_Vol": {
      "parents": [],
      "parameters": null,
      "distribution": "(-0.15764961890824067, 0.9683411562341923)"
    },
    "Age": {
      "parents": [],
      "parameters": null,
      "distribution": "(1.2333333333333334, 0.7340905181848414)"
    },
    "Gender": {
      "parents": [],
      "parameters": null,
      "distribution": "(0.4266666666666667, 0.49459298642643756)"
    },
    "CogFluidComp_Unadj": {
      "parents": [
        "FS_Total_GM_Vol",
        "FS_Tot_WM_Vol"
      ],
      "parameters": null,
      "distribution": "(array([-0.07485438,  0.2503824 , -0.04472499]), 0.0)"
    },
    "CogCrystalComp_Unadj": {
      "parents": [
        "FS_Total_GM_Vol",
        "FS_Tot_WM_Vol"
      ],
      "parameters": null,
      "distribution": "(array([0.00409942, 0.2772056 , 0.0148876 ]), 0.0)"
    },
    "MMSE_Score": {
      "parents": [
        "Age"
      ],
      "parameters": null,
      "distribution": "(array([29.05080412, -0.04659794]), 0.0)"
    },
    "NEOFAC_O": {
      "parents": [
        "FS_L_Hippo_Vol",
        "FS_R_Hippo_Vol"
      ],
      "parameters": null,
      "distribution": "(array([ 0.00297541, -0.07765327,  0.26150378]), 0.0)"
    },
    "NEOFAC_C": {
      "parents": [],
      "parameters": null,
      "distribution": "(-0.07524350931569611, 0.9626486152145997)"
    },
    "ProcSpeed_Unadj": {
      "parents": [],
      "parameters": null,
      "distribution": "(-0.10762833829448219, 1.018501663461804)"
    },
    "CardSort_Unadj": {
      "parents": [],
      "parameters": null,
      "distribution": "(-0.16613434824066117, 0.9461432398900251)"
    },
    "PicVocab_Unadj": {
      "parents": [],
      "parameters": null,
      "distribution": "(0.0029424877165653267, 1.058801292621294)"
    },
    "ReadEng_Unadj": {
      "parents": [],
      "parameters": null,
      "distribution": "(0.010172146681844343, 1.038117773081238)"
    }
  },
  "sensitivity": {
    "CogFluidComp_Unadj": {
      "FS_TotCort_GM_Vol": -0.060807889165002946,
      "FS_SubCort_GM_Vol": -0.2934919074702248,
      "FS_Total_GM_Vol": -0.2834999860502117,
      "FS_Tot_WM_Vol": 0.10277259725762401,
      "FS_BrainStem_Vol": -0.3989043194491774,
      "FS_L_Hippo_Vol": -0.08767365429756352,
      "FS_R_Hippo_Vol": -0.10116341509037408,
      "FS_L_Amygdala_Vol": -0.19662119250214485,
      "FS_R_Amygdala_Vol": -0.2844503427495769,
      "FS_L_Caudate_Vol": -0.044123936878337024,
      "FS_R_Caudate_Vol": -0.026025019258708128,
      "FS_L_Putamen_Vol": -0.3256268644402182,
      "FS_R_Putamen_Vol": -0.36157330986096764,
      "Age": 2.8286805802857744,
      "Gender": 0.9785705791258895,
      "CogCrystalComp_Unadj": 0.22644170751228918,
      "MMSE_Score": 33.260933020426236,
      "NEOFAC_O": 0.14282995864582604,
      "NEOFAC_C": -0.172572854265293,
      "ProcSpeed_Unadj": -0.24684826250434827,
      "CardSort_Unadj": -0.3810332469622641,
      "PicVocab_Unadj": 0.00674866853641441,
      "ReadEng_Unadj": 0.02333007063142011
    },
    "CogCrystalComp_Unadj": {
      "FS_TotCort_GM_Vol": -0.026853661294575268,
      "FS_SubCort_GM_Vol": -0.12961035786850209,
      "FS_Total_GM_Vol": -0.13861008276054812,
      "FS_Tot_WM_Vol": -0.015107594970652246,
      "FS_BrainStem_Vol": -0.1761620347380257,
      "FS_L_Hippo_Vol": -0.03871797967819396,
      "FS_R_Hippo_Vol": -0.044675257134282054,
      "FS_L_Amygdala_Vol": -0.08683082046246893,
      "FS_R_Amygdala_Vol": -0.12561746944702734,
      "FS_L_Caudate_Vol": -0.01948578173300622,
      "FS_R_Caudate_Vol": -0.01149303259749343,
      "FS_L_Putamen_Vol": -0.1438016291334255,
      "FS_R_Putamen_Vol": -0.15967610995043602,
      "Age": 1.2491870916192678,
      "Gender": 0.43215121007369267,
      "CogFluidComp_Unadj": 0.04416147585999497,
      "MMSE_Score": 14.688518906624628,
      "NEOFAC_O": 0.06307581770821725,
      "NEOFAC_C": -0.07621071937727165,
      "ProcSpeed_Unadj": -0.10901183585667476,
      "CardSort_Unadj": -0.16826990537579528,
      "PicVocab_Unadj": 0.002980311626579725,
      "ReadEng_Unadj": 0.010302903510014366
    }
  },
  "insights": [
    "The top 3 predictors of CogFluidComp_Unadj are: MMSE_Score (sensitivity: 33.261), Age (sensitivity: 2.829), Gender (sensitivity: 0.979)",
    "The top 3 predictors of CogCrystalComp_Unadj are: MMSE_Score (sensitivity: 14.689), Age (sensitivity: 1.249), Gender (sensitivity: 0.432)",
    "Age directly influences: CogFluidComp_Unadj, CogCrystalComp_Unadj, MMSE_Score",
    "Gender directly influences: CogFluidComp_Unadj, CogCrystalComp_Unadj",
    "Key brain structure-cognition relationships: FS_Total_GM_Vol \u2192 CogFluidComp_Unadj, FS_Tot_WM_Vol \u2192 CogFluidComp_Unadj, FS_Total_GM_Vol \u2192 CogCrystalComp_Unadj, FS_Tot_WM_Vol \u2192 CogCrystalComp_Unadj"
  ]
}